{
  "siteTitle": "Java Missing Book",
  "repoRoot": "/Users/indiadelhi/repo/career/java-missing-tutorial/code",
  "generatedAt": "2026-04-07T22:00:56Z",
  "stats": {
    "sections": 22,
    "chapters": 56,
    "topics": 107
  },
  "resources": [
    {"slug": "README", "title": "README", "sourcePath": "README.md", "contentPath": "content/meta/README.md", "type": "markdown"},
    {"slug": "BOOK", "title": "BOOK", "sourcePath": "planning/BOOK.md", "contentPath": "content/meta/BOOK.md", "type": "markdown"},
    {"slug": "CURRICULUM", "title": "CURRICULUM", "sourcePath": "planning/CURRICULUM.md", "contentPath": "content/meta/CURRICULUM.md", "type": "markdown"},
    {"slug": "ROADMAP_099", "title": "ROADMAP 099", "sourcePath": "planning/ROADMAP_099.md", "contentPath": "content/meta/ROADMAP_099.md", "type": "markdown"},
    {"slug": "TOP_20_BOOKS", "title": "TOP 20 BOOKS", "sourcePath": "planning/TOP_20_BOOKS.md", "contentPath": "content/meta/TOP_20_BOOKS.md", "type": "markdown"},
    {"slug": "AUTHORING_GUIDE", "title": "AUTHORING GUIDE", "sourcePath": "planning/AUTHORING_GUIDE.md", "contentPath": "content/meta/AUTHORING_GUIDE.md", "type": "markdown"},
    {"slug": "INTERVIEW_TOPIC_TEMPLATE", "title": "INTERVIEW TOPIC TEMPLATE", "sourcePath": "planning/INTERVIEW_TOPIC_TEMPLATE.md", "contentPath": "content/meta/INTERVIEW_TOPIC_TEMPLATE.md", "type": "markdown"},
    {"slug": "CERTIFICATION_TOPIC_TEMPLATE", "title": "CERTIFICATION TOPIC TEMPLATE", "sourcePath": "planning/CERTIFICATION_TOPIC_TEMPLATE.md", "contentPath": "content/meta/CERTIFICATION_TOPIC_TEMPLATE.md", "type": "markdown"},
    {"slug": "VISUAL_LESSON_STANDARD", "title": "VISUAL LESSON STANDARD", "sourcePath": "planning/VISUAL_LESSON_STANDARD.md", "contentPath": "content/meta/VISUAL_LESSON_STANDARD.md", "type": "markdown"},
    {"slug": "CHAPTER_QUALITY_CHECKLIST", "title": "CHAPTER QUALITY CHECKLIST", "sourcePath": "planning/CHAPTER_QUALITY_CHECKLIST.md", "contentPath": "content/meta/CHAPTER_QUALITY_CHECKLIST.md", "type": "markdown"},
    {"slug": "TOPIC_QUALITY_RUBRIC", "title": "TOPIC QUALITY RUBRIC", "sourcePath": "planning/TOPIC_QUALITY_RUBRIC.md", "contentPath": "content/meta/TOPIC_QUALITY_RUBRIC.md", "type": "markdown"},
    {"slug": "DEEP_DIVE_STANDARD", "title": "DEEP DIVE STANDARD", "sourcePath": "planning/DEEP_DIVE_STANDARD.md", "contentPath": "content/meta/DEEP_DIVE_STANDARD.md", "type": "markdown"},
    {"slug": "BOOK_MANUSCRIPT", "title": "BOOK MANUSCRIPT", "sourcePath": "planning/BOOK_MANUSCRIPT.md", "contentPath": "content/meta/BOOK_MANUSCRIPT.md", "type": "markdown"},
    {"slug": "JAVA_7_TO_25", "title": "JAVA 7 TO 25", "sourcePath": "planning/JAVA_7_TO_25.md", "contentPath": "content/meta/JAVA_7_TO_25.md", "type": "markdown"},
    {"slug": "JAVA_MIGRATION_GUIDES", "title": "JAVA MIGRATION GUIDES", "sourcePath": "planning/JAVA_MIGRATION_GUIDES.md", "contentPath": "content/meta/JAVA_MIGRATION_GUIDES.md", "type": "markdown"},
    {"slug": "HIGH_DEMAND_JAVA_TOPICS", "title": "HIGH DEMAND JAVA TOPICS", "sourcePath": "planning/HIGH_DEMAND_JAVA_TOPICS.md", "contentPath": "content/meta/HIGH_DEMAND_JAVA_TOPICS.md", "type": "markdown"},
